KMeansKTran/__init__.py
KMeansKTran/kmeans.py
KMeansKTran-0.0.1.dist-info/LICENSE.txt
KMeansKTran-0.0.1.dist-info/METADATA
KMeansKTran-0.0.1.dist-info/WHEEL
KMeansKTran-0.0.1.dist-info/top_level.txt
KMeansKTran-0.0.1.dist-info/RECORD
