Metadata-Version: 2.1
Name: KMeansKTran
Version: 0.0.1
Summary: K-Means Clustering Package to return best K using Silhouette Analysis
Home-page: https://github.com/KTranKHS/KMeans_BCM
Author: Kevin Tran
Author-email: KTranKHS@gmail.com
License: UNKNOWN
Platform: UNKNOWN
Classifier: Programming Language :: Python :: 3.7
Requires-Python: >=3.7.4
